[{"player":"Keshunn Abram","no":null,"pos":"WR","status":"ACT","height":"74","weight":"193","experience":"R","college":"Kent State","team":"new york jets"},{"player":"Rodney Adams","no":null,"pos":"WR","status":"ACT","height":"73","weight":"189","experience":"2","college":"University of South Florida","team":"new york jets"},{"player":"Tony Adams","no":null,"pos":"DB","status":"ACT","height":"72","weight":"205","experience":"R","college":"Illinois","team":"new york jets"},{"player":"Bradlee Anae","no":null,"pos":"DE","status":"ACT","height":"75","weight":"260","experience":"3","college":"Utah","team":"new york jets"},{"player":"Nick Bawden","no":"46","pos":"RB","status":"ACT","height":"74","weight":"245","experience":"5","college":"San Diego State","team":"new york jets"},{"player":"Mekhi Becton","no":"77","pos":"OT","status":"ACT","height":"79","weight":"363","experience":"3","college":"Louisville","team":"new york jets"},{"player":"Tarik Black","no":"3","pos":"WR","status":"ACT","height":"75","weight":"213","experience":"1","college":"Texas","team":"new york jets"},{"player":"Lawrence Cager","no":null,"pos":"WR","status":"ACT","height":"77","weight":"220","experience":"2","college":"Georgia","team":"new york jets"},{"player":"Michael Carter","no":"32","pos":"RB","status":"ACT","height":"68","weight":"201","experience":"2","college":"North Carolina","team":"new york jets"},{"player":"Michael Carter II","no":"30","pos":"CB","status":"ACT","height":"70","weight":"184","experience":"2","college":"Duke","team":"new york jets"},{"player":"Irvin Charles","no":null,"pos":"WR","status":"ACT","height":"76","weight":"219","experience":"R","college":"Indiana PA, University of","team":"new york jets"},{"player":"Tevin Coleman","no":"23","pos":"RB","status":"ACT","height":"73","weight":"210","experience":"8","college":"Indiana","team":"new york jets"},{"player":"Tyler Conklin","no":null,"pos":"TE","status":"ACT","height":"75","weight":"248","experience":"5","college":"Central Michigan","team":"new york jets"},{"player":"Vinny Curry","no":"99","pos":"DE","status":"ACT","height":"75","weight":"279","experience":"11","college":"Marshall","team":"new york jets"},{"player":"Ashtyn Davis","no":"21","pos":"SAF","status":"ACT","height":"73","weight":"202","experience":"3","college":"California","team":"new york jets"},{"player":"Corey Davis","no":"84","pos":"WR","status":"ACT","height":"75","weight":"209","experience":"6","college":"Western Michigan","team":"new york jets"},{"player":"Isaiah Dunn","no":"27","pos":"CB","status":"ACT","height":"72","weight":"193","experience":"2","college":"Oregon State","team":"new york jets"},{"player":"Brandin Echols","no":"26","pos":"CB","status":"ACT","height":"70","weight":"179","experience":"2","college":"Kentucky","team":"new york jets"},{"player":"Chuma Edoga","no":"70","pos":"OT","status":"ACT","height":"75","weight":"308","experience":"4","college":"USC","team":"new york jets"},{"player":"George Fant","no":"76","pos":"OT","status":"ACT","height":"77","weight":"322","experience":"7","college":"Western Kentucky","team":"new york jets"},{"player":"Dan Feeney","no":"67","pos":"G","status":"ACT","height":"76","weight":"310","experience":"6","college":"Indiana","team":"new york jets"},{"player":"Parker Ferguson","no":null,"pos":"G","status":"ACT","height":"77","weight":"290","experience":"2","college":"Air Force","team":"new york jets"},{"player":"Joe Flacco","no":"19","pos":"QB","status":"ACT","height":"78","weight":"245","experience":"15","college":"Delaware","team":"new york jets"},{"player":"John Franklin-Myers","no":"91","pos":"DE","status":"ACT","height":"76","weight":"288","experience":"5","college":"Stephen F. Austin State","team":"new york jets"},{"player":"Sauce Gardner","no":null,"pos":"CB","status":"ACT","height":"75","weight":"200","experience":"R","college":"Cincinnati","team":"new york jets"},{"player":"Javelin Guidry","no":"40","pos":"CB","status":"ACT","height":"69","weight":"191","experience":"3","college":"Utah","team":"new york jets"},{"player":"Bryce Hall","no":"37","pos":"CB","status":"ACT","height":"73","weight":"202","experience":"3","college":"Virginia","team":"new york jets"},{"player":"Justin Hardee","no":"34","pos":"DB","status":"ACT","height":"73","weight":"200","experience":"6","college":"Illinois","team":"new york jets"},{"player":"Marcell Harris","no":null,"pos":"LB","status":"ACT","height":"72","weight":"215","experience":"5","college":"Florida","team":"new york jets"},{"player":"Thomas Hennessy","no":"42","pos":"LS","status":"ACT","height":"74","weight":"246","experience":"6","college":"Duke","team":"new york jets"},{"player":"Nate Herbig","no":null,"pos":"G","status":"ACT","height":"76","weight":"334","experience":"4","college":"Stanford","team":"new york jets"},{"player":"Grant Hermanns","no":"78","pos":"OT","status":"ACT","height":"79","weight":"300","experience":"1","college":"Purdue","team":"new york jets"},{"player":"Bryce Huff","no":"47","pos":"DE","status":"ACT","height":"75","weight":"255","experience":"3","college":"Memphis","team":"new york jets"},{"player":"Calvin Jackson","no":null,"pos":"WR","status":"ACT","height":"70","weight":"194","experience":"R","college":"Washington State","team":"new york jets"},{"player":"Ty Johnson","no":"25","pos":"RB","status":"ACT","height":"70","weight":"210","experience":"4","college":"Maryland","team":"new york jets"},{"player":"Lamarcus Joyner","no":"29","pos":"FS","status":"ACT","height":"68","weight":"185","experience":"9","college":"Florida State","team":"new york jets"},{"player":"Derrick Kelly","no":null,"pos":"OT","status":"ACT","height":"77","weight":"320","experience":"2","college":"Florida State","team":"new york jets"},{"player":"Bam Knight","no":null,"pos":"RB","status":"ACT","height":"71","weight":"210","experience":"R","college":"N.C. State","team":"new york jets"},{"player":"Carl Lawson","no":"58","pos":"DE","status":"ACT","height":"74","weight":"265","experience":"6","college":"Auburn","team":"new york jets"},{"player":"Braden Mann","no":"7","pos":"P","status":"ACT","height":"71","weight":"198","experience":"3","college":"Texas A&M","team":"new york jets"},{"player":"Jonathan Marshall","no":"96","pos":"DT","status":"ACT","height":"75","weight":"310","experience":"2","college":"Arkansas","team":"new york jets"},{"player":"Jake Martin","no":null,"pos":"DE","status":"ACT","height":"74","weight":"242","experience":"4","college":"Temple","team":"new york jets"},{"player":"Conor McDermott","no":"69","pos":"OT","status":"ACT","height":"80","weight":"310","experience":"6","college":"UCLA","team":"new york jets"},{"player":"Connor McGovern","no":"60","pos":"G","status":"ACT","height":"76","weight":"306","experience":"7","college":"Missouri","team":"new york jets"},{"player":"Denzel Mims","no":"11","pos":"WR","status":"ACT","height":"75","weight":"207","experience":"3","college":"Baylor","team":"new york jets"},{"player":"Jovante Moffatt","no":null,"pos":"SAF","status":"ACT","height":"71","weight":"213","experience":"2","college":"Middle Tennessee State","team":"new york jets"},{"player":"Elijah Moore","no":"8","pos":"WR","status":"ACT","height":"70","weight":"178","experience":"2","college":"Mississippi","team":"new york jets"},{"player":"C.J. Mosley","no":"57","pos":"ILB","status":"ACT","height":"74","weight":"250","experience":"8","college":"Alabama","team":"new york jets"},{"player":"Kai Nacua","no":"1","pos":"DB","status":"ACT","height":"72","weight":"205","experience":"3","college":"BYU","team":"new york jets"},{"player":"Hamsah Nasirildeen","no":"45","pos":"LB","status":"ACT","height":"75","weight":"215","experience":"2","college":"Florida State","team":"new york jets"},{"player":"Will Parks","no":"39","pos":"S","status":"ACT","height":"72","weight":"200","experience":"7","college":"Arizona","team":"new york jets"},{"player":"La'Mical Perine","no":"22","pos":"RB","status":"ACT","height":"71","weight":"216","experience":"3","college":"Florida","team":"new york jets"},{"player":"Del'Shawn Phillips","no":"43","pos":"LB","status":"ACT","height":"74","weight":"230","experience":"3","college":"Illinois","team":"new york jets"},{"player":"Ross Pierschbacher","no":"66","pos":"C","status":"ACT","height":"76","weight":"315","experience":"2","college":"Alabama","team":"new york jets"},{"player":"Eddy Pineiro","no":"15","pos":"K","status":"ACT","height":"72","weight":"185","experience":"4","college":"Florida","team":"new york jets"},{"player":"Jason Pinnock","no":"41","pos":"CB","status":"ACT","height":"72","weight":"205","experience":"2","college":"Pittsburgh","team":"new york jets"},{"player":"Sheldon Rankins","no":"98","pos":"DT","status":"ACT","height":"74","weight":"305","experience":"7","college":"Louisville","team":"new york jets"},{"player":"Hamilcar Rashed Jr.","no":"55","pos":"DE","status":"ACT","height":"74","weight":"251","experience":"1","college":"Oregon State","team":"new york jets"},{"player":"D.J. Reed","no":null,"pos":"FS","status":"ACT","height":"69","weight":"193","experience":"5","college":"Kansas State","team":"new york jets"},{"player":"Elijah Riley","no":"33","pos":"DB","status":"ACT","height":"72","weight":"205","experience":"2","college":"Army","team":"new york jets"},{"player":"Dru Samia","no":null,"pos":"G","status":"ACT","height":"77","weight":"308","experience":"3","college":"Oklahoma","team":"new york jets"},{"player":"Greg Senat","no":null,"pos":"OT","status":"ACT","height":"78","weight":"305","experience":"4","college":"Wagner","team":"new york jets"},{"player":"Nathan Shepherd","no":"97","pos":"DE","status":"ACT","height":"76","weight":"315","experience":"5","college":"Fort Hays","team":"new york jets"},{"player":"Jamien Sherwood","no":"44","pos":"LB","status":"ACT","height":"74","weight":"216","experience":"2","college":"Auburn","team":"new york jets"},{"player":"Tanzel Smart","no":"79","pos":"DT","status":"ACT","height":"73","weight":"295","experience":"4","college":"Tulane","team":"new york jets"},{"player":"Jeff Smith","no":"16","pos":"WR","status":"ACT","height":"73","weight":"195","experience":"3","college":"Boston College","team":"new york jets"},{"player":"DQ Thomas","no":null,"pos":"LB","status":"ACT","height":"74","weight":"216","experience":"R","college":"Middle Tennessee State","team":"new york jets"},{"player":"Solomon Thomas","no":null,"pos":"DE","status":"ACT","height":"75","weight":"295","experience":"6","college":"Stanford","team":"new york jets"},{"player":"Laken Tomlinson","no":null,"pos":"G","status":"ACT","height":"75","weight":"315","experience":"8","college":"Duke","team":"new york jets"},{"player":"C.J. Uzomah","no":null,"pos":"TE","status":"ACT","height":"78","weight":"260","experience":"8","college":"Auburn","team":"new york jets"},{"player":"Alijah Vera-Tucker","no":"75","pos":"G","status":"ACT","height":"77","weight":"308","experience":"2","college":"USC","team":"new york jets"},{"player":"Tim Ward","no":"51","pos":"DE","status":"ACT","height":"78","weight":"255","experience":"3","college":"Old Dominion","team":"new york jets"},{"player":"Trevon Wesco","no":"85","pos":"TE","status":"ACT","height":"75","weight":"267","experience":"4","college":"West Virginia","team":"new york jets"},{"player":"Javin White","no":"9","pos":"LB","status":"ACT","height":"74","weight":"211","experience":"2","college":"UNLV","team":"new york jets"},{"player":"Mike White","no":"5","pos":"QB","status":"ACT","height":"77","weight":"218","experience":"4","college":"Western Kentucky","team":"new york jets"},{"player":"Jordan Whitehead","no":null,"pos":"FS","status":"ACT","height":"70","weight":"198","experience":"5","college":"Pittsburgh","team":"new york jets"},{"player":"Rachad Wildgoose","no":"29","pos":"CB","status":"ACT","height":"70","weight":"191","experience":"2","college":"Wisconsin","team":"new york jets"},{"player":"Quinnen Williams","no":"95","pos":"DT","status":"ACT","height":"75","weight":"303","experience":"4","college":"Alabama","team":"new york jets"},{"player":"Quincy Williams","no":"56","pos":"LB","status":"ACT","height":"71","weight":"230","experience":"4","college":"Murray State","team":"new york jets"},{"player":"Zach Wilson","no":"2","pos":"QB","status":"ACT","height":"74","weight":"214","experience":"2","college":"BYU","team":"new york jets"},{"player":"Kenny Yeboah","no":"48","pos":"TE","status":"ACT","height":"75","weight":"250","experience":"2","college":"Mississippi","team":"new york jets"},{"player":"Greg Zuerlein","no":null,"pos":"K","status":"ACT","height":"72","weight":"197","experience":"11","college":"Missouri Western","team":"new york jets"},{"player":"Jabari Zuniga","no":"92","pos":"DE","status":"ACT","height":"75","weight":"264","experience":"2","college":"Florida","team":"new york jets"},{"player":"Zane Lewis","no":"33","pos":"CB","status":"PUP","height":"73","weight":"190","experience":"2","college":"Air Force","team":"new york jets"},{"player":"Kyle Phillips","no":"93","pos":"DE","status":"RFA","height":"76","weight":"277","experience":"4","college":"Tennessee","team":"new york jets"},{"player":"Micheal Clemons","no":null,"pos":"DE","status":"UDF","height":"77","weight":"270","experience":"R","college":"Texas A&M","team":"new york jets"},{"player":"Breece Hall","no":null,"pos":"RB","status":"UDF","height":"73","weight":"220","experience":"R","college":"Iowa State","team":"new york jets"},{"player":"Jermaine Johnson II","no":null,"pos":"DE","status":"UDF","height":"77","weight":"262","experience":"R","college":"Florida State","team":"new york jets"},{"player":"Max Mitchell","no":null,"pos":"OT","status":"UDF","height":"78","weight":"299","experience":"R","college":"Louisiana","team":"new york jets"},{"player":"Jeremy Ruckert","no":null,"pos":"TE","status":"UDF","height":"77","weight":"250","experience":"R","college":"Ohio State","team":"new york jets"},{"player":"Garrett Wilson","no":null,"pos":"WR","status":"UDF","height":"72","weight":"192","experience":"R","college":"Ohio State","team":"new york jets"},{"player":"Matt Ammendola","no":null,"pos":"K","status":"UFA","height":"69","weight":"195","experience":"2","college":"Oklahoma State","team":"new york jets"},{"player":"Braxton Berrios","no":"10","pos":"WR","status":"UFA","height":"69","weight":"190","experience":"5","college":"Miami","team":"new york jets"},{"player":"Cameron Clarke","no":"72","pos":"G","status":"UFA","height":"76","weight":"308","experience":"3","college":"Charlotte","team":"new york jets"},{"player":"Keelan Cole","no":"88","pos":"WR","status":"UFA","height":"73","weight":"194","experience":"6","college":"Kentucky Wesleyan","team":"new york jets"},{"player":"Brandon Dillon","no":null,"pos":"TE","status":"UFA","height":"77","weight":"250","experience":"1","college":"Marian","team":"new york jets"},{"player":"Laurent Duvernay-Tardif","no":"72","pos":"G","status":"UFA","height":"77","weight":"321","experience":"8","college":"McGill","team":"new york jets"},{"player":"Tyler Kroft","no":"81","pos":"TE","status":"UFA","height":"78","weight":"252","experience":"8","college":"Rutgers","team":"new york jets"},{"player":"D.J. Montgomery","no":"14","pos":"WR","status":"UFA","height":"73","weight":"201","experience":"2","college":"Austin Peay","team":"new york jets"},{"player":"Greg Van Roten","no":"62","pos":"G","status":"UFA","height":"75","weight":"305","experience":"8","college":"Penn","team":"new york jets"},{"player":"Austin Walter","no":"36","pos":"RB","status":"UFA","height":"68","weight":"202","experience":"3","college":"Rice","team":"new york jets"}]